README.rst
carioca
pyproject.toml
setup.py
carioca/SAM_BA.py
carioca/TTY.py
carioca/__init__.py
carioca/carioca.py
carioca/commands.py
carioca/version.py
carioca.egg-info/PKG-INFO
carioca.egg-info/SOURCES.txt
carioca.egg-info/dependency_links.txt
carioca.egg-info/entry_points.txt
carioca.egg-info/requires.txt
carioca.egg-info/top_level.txt