Metadata-Version: 2.1
Name: carioca
Version: 1.0.2
Summary: Interface to Atmel SAM-BA Monitor.
Home-page: https://bitbucket.org/egauge/carioca/
Author: David Mosberger-Tang
Author-email: davidm@egauge.net
License: MIT License
Classifier: Development Status :: 5 - Production/Stable
